Ds_Style/Ds_Style.py
Ds_Style/__init__.py
Ds_Style-0.0.1.dist-info/LICENSE
Ds_Style-0.0.1.dist-info/METADATA
Ds_Style-0.0.1.dist-info/WHEEL
Ds_Style-0.0.1.dist-info/top_level.txt
Ds_Style-0.0.1.dist-info/RECORD
