Metadata-Version: 2.1
Name: Ds-Style
Version: 0.0.1
Summary: Style linux Tools
Home-page: https://github.com/DARK-STORM101
Author: Dark Storm
Author-email: darkstorm048@gmail.com
Project-URL: Bug Tracker, https://github.com/DARK-STORM101/Ds-Hash.git
Classifier: Programming Language :: Python :: 3
Classifier: License :: OSI Approved :: MIT License
Classifier: Operating System :: OS Independent
Requires-Python: >=3.6
License-File: LICENSE
